zzz/DrawFigure.py
zzz/__init__.py
DrawFigure-0.0.3.dist-info/LICENSE
DrawFigure-0.0.3.dist-info/METADATA
DrawFigure-0.0.3.dist-info/WHEEL
DrawFigure-0.0.3.dist-info/top_level.txt
DrawFigure-0.0.3.dist-info/RECORD
